testgen/__init__.py
testgen/__main__.py
testgen/settings.py
testgen/commands/__init__.py
testgen/commands/run_execute_cat_tests.py
testgen/commands/run_execute_tests.py
testgen/commands/run_generate_tests.py
testgen/commands/run_get_entities.py
testgen/commands/run_launch_db_config.py
testgen/commands/run_observability_exporter.py
testgen/commands/run_profiling_bridge.py
testgen/commands/run_quick_start.py
testgen/commands/run_setup_profiling_tools.py
testgen/commands/run_test_definition.py
testgen/commands/run_test_parameter_validation.py
testgen/commands/run_upgrade_db_config.py
testgen/commands/queries/__init__.py
testgen/commands/queries/execute_cat_tests_query.py
testgen/commands/queries/execute_tests_query.py
testgen/commands/queries/generate_tests_query.py
testgen/commands/queries/profiling_query.py
testgen/commands/queries/test_parameter_validation_query.py
testgen/common/__init__.py
testgen/common/clean_sql.py
testgen/common/credentials.py
testgen/common/date_service.py
testgen/common/display_service.py
testgen/common/docker_service.py
testgen/common/encrypt.py
testgen/common/get_pipeline_parms.py
testgen/common/logs.py
testgen/common/process_service.py
testgen/common/read_file.py
testgen/common/database/__init__.py
testgen/common/database/database_service.py
testgen/common/database/flavor/__init__.py
testgen/common/database/flavor/flavor_service.py
testgen/common/database/flavor/mssql_flavor_service.py
testgen/common/database/flavor/postgresql_flavor_service.py
testgen/common/database/flavor/redshift_flavor_service.py
testgen/common/database/flavor/snowflake_flavor_service.py
testgen/common/database/flavor/trino_flavor_service.py
testgen/template/dbsetup/010_create_base_schema.sql
testgen/template/dbsetup/020_create_standard_functions_sprocs.sql
testgen/template/dbsetup/030_initialize_new_schema_structure.sql
testgen/template/dbsetup/040_populate_new_schema_project.sql
testgen/template/dbsetup/050_populate_new_schema_metadata.sql
data_ops_testgen-2.2.1.dist-info/LICENSE
data_ops_testgen-2.2.1.dist-info/METADATA
data_ops_testgen-2.2.1.dist-info/NOTICE
data_ops_testgen-2.2.1.dist-info/WHEEL
data_ops_testgen-2.2.1.dist-info/entry_points.txt
data_ops_testgen-2.2.1.dist-info/top_level.txt
data_ops_testgen-2.2.1.dist-info/RECORD
