Metadata-Version: 2.1
Name: data-ops-testgen
Version: 2.2.1
Summary: DataKitchen Inc. Data Quality Engine
Author-email: Charles Bloche <chip@datakitchen.io>, Tyler Stubenvoll <tstubenvoll@datakitchen.io>, Alejandro Fernandez <alex@datakitchen.io>, Anuja Waikar <awaikar@datakitchen.io>, Shruthy Vakkil <svakkil@datakitchen.io>, Arnob Bordoloi <abordoloi@datakitchen.io>, Saurabh Vashist <svashist@datakitchen.io>, Saurabh Vaidya <saurabh@datakitchen.io>
License: CLOSED
Project-URL: homepage, https://datakitchen.io
Classifier: Intended Audience :: Developers
Classifier: Operating System :: OS Independent
Classifier: Programming Language :: Python
Classifier: Programming Language :: Python :: 3.10
Requires-Python: >=3.10
License-File: LICENSE
License-File: NOTICE
Requires-Dist: PyYAML ==6.0.1
Requires-Dist: click ==8.1.3
Requires-Dist: sqlalchemy ==1.4.46
Requires-Dist: snowflake-sqlalchemy ==1.4.7
Requires-Dist: pyodbc ==4.0.39
Requires-Dist: psycopg2-binary ==2.9.6
Requires-Dist: pycryptodome ==3.17
Requires-Dist: prettytable ==3.7.0
Requires-Dist: requests-extensions ==1.1.3
Requires-Dist: bz2file ==0.98
Requires-Dist: trogon ==0.4.0
Requires-Dist: numpy ==1.25.2
Requires-Dist: pandas ==2.1.0
Requires-Dist: streamlit ==1.26.0
Requires-Dist: streamlit-extras ==0.3.0
Requires-Dist: streamlit-aggrid ==0.3.4.post3
Requires-Dist: streamlit-antd-components ==0.2.2
Requires-Dist: streamlit-plotly-events ==0.0.6
Requires-Dist: plotly-express ==0.4.1
Requires-Dist: streamlit-option-menu ==0.3.6
Requires-Dist: streamlit-authenticator ==0.2.3
Requires-Dist: streamlit-javascript ==0.1.5
Requires-Dist: streamlit-modal ==0.1.0
Requires-Dist: progress ==1.6
Requires-Dist: beautifulsoup4 ==4.12.3
Requires-Dist: trino ==0.327.0
Requires-Dist: xlsxwriter ==3.2.0
Requires-Dist: psutil ==5.9.8
Requires-Dist: concurrent-log-handler ==0.9.25
Requires-Dist: cryptography ==42.0.8
Provides-Extra: dev
Requires-Dist: invoke ==2.2.0 ; extra == 'dev'
Requires-Dist: ruff ==0.4.1 ; extra == 'dev'
Requires-Dist: mypy ==1.9.0 ; extra == 'dev'
Requires-Dist: pre-commit ==3.6.2 ; extra == 'dev'
Requires-Dist: types-PyYAML ==6.0.12.20240311 ; extra == 'dev'
Requires-Dist: types-setuptools ==69.2.0.20240317 ; extra == 'dev'
Requires-Dist: semver ==3.0.2 ; extra == 'dev'
Requires-Dist: pytest ==8.1.1 ; extra == 'dev'
Requires-Dist: pytest-cov ==4.1.0 ; extra == 'dev'
Requires-Dist: tomli ==2.0.1 ; extra == 'dev'
Provides-Extra: release
Requires-Dist: bumpver ==2023.1129 ; extra == 'release'
